setup.py
peewee_filters/__init__.py
peewee_filters/_filterops.py
peewee_filters/exceptions.py
peewee_filters/filters.py
peewee_filters/filterset.py
peewee_filters/utils.py
peewee_filters.egg-info/PKG-INFO
peewee_filters.egg-info/SOURCES.txt
peewee_filters.egg-info/dependency_links.txt
peewee_filters.egg-info/not-zip-safe
peewee_filters.egg-info/requires.txt
peewee_filters.egg-info/top_level.txt