Metadata-Version: 1.0
Name: peewee-filters
Version: 0.0.2
Summary: Generating peewee query expression against json payload.
Home-page: https://github.com/wonderbeyond/peewee_filters
Author: wonderbeyond
Author-email: UNKNOWN
License: UNKNOWN
Platform: UNKNOWN
